confidence_intervals/__init__.py
confidence_intervals/confidence_intervals.py
confidence_intervals/utils.py
confidence_intervals-0.0.3.dist-info/LICENSE
confidence_intervals-0.0.3.dist-info/METADATA
confidence_intervals-0.0.3.dist-info/WHEEL
confidence_intervals-0.0.3.dist-info/top_level.txt
confidence_intervals-0.0.3.dist-info/RECORD
