Metadata-Version: 2.1
Name: confidence-intervals
Version: 0.0.3
Summary: Toolkit for computing confidence intervals for system evaluation with the bootstrapping appproach
Home-page: https://github.com/luferrer/ConfidenceIntervals
Author: Luciana Ferrer
Author-email: lferrer@dc.uba.ar
Classifier: Programming Language :: Python :: 3
Classifier: License :: OSI Approved :: MIT License
Classifier: Operating System :: OS Independent
Requires-Python: >=3.6
License-File: LICENSE
Requires-Dist: numpy >=1.24.1
Requires-Dist: scikit-learn >=1.2.2
